dotcon/__init__.py
dotcon-0.5.1.dist-info/LICENSE
dotcon-0.5.1.dist-info/METADATA
dotcon-0.5.1.dist-info/WHEEL
dotcon-0.5.1.dist-info/RECORD
