Metadata-Version: 2.1
Name: dotcon
Version: 0.5.1
Summary: A simple package which converts a standard python dictionary to a dot accessible object.
License: LICENCE
Author: AidanInceer
Author-email: aidaninceer0@gmail.com
Requires-Python: >=3.11,<4.0
Classifier: License :: Other/Proprietary License
Classifier: Programming Language :: Python :: 3
Classifier: Programming Language :: Python :: 3.11
Classifier: Programming Language :: Python :: 3.12
Requires-Dist: pre-commit (>=3.7.0,<4.0.0)
Requires-Dist: pytest (>=8.1.1,<9.0.0)
